odoo/addons/account_fiscal_position_partner_type/README.rst
odoo/addons/account_fiscal_position_partner_type/__init__.py
odoo/addons/account_fiscal_position_partner_type/__manifest__.py
odoo/addons/account_fiscal_position_partner_type/i18n/account_fiscal_position_partner_type.pot
odoo/addons/account_fiscal_position_partner_type/models/__init__.py
odoo/addons/account_fiscal_position_partner_type/models/account_fiscal_position.py
odoo/addons/account_fiscal_position_partner_type/models/res_company.py
odoo/addons/account_fiscal_position_partner_type/models/res_partner.py
odoo/addons/account_fiscal_position_partner_type/readme/CONFIGURE.rst
odoo/addons/account_fiscal_position_partner_type/readme/CONTRIBUTORS.rst
odoo/addons/account_fiscal_position_partner_type/readme/DESCRIPTION.rst
odoo/addons/account_fiscal_position_partner_type/readme/USAGE.rst
odoo/addons/account_fiscal_position_partner_type/static/description/icon.png
odoo/addons/account_fiscal_position_partner_type/static/description/index.html
odoo/addons/account_fiscal_position_partner_type/tests/__init__.py
odoo/addons/account_fiscal_position_partner_type/tests/test_account_fiscal_position_partner_type.py
odoo/addons/account_fiscal_position_partner_type/views/account_fiscal_position.xml
odoo/addons/account_fiscal_position_partner_type/views/res_company.xml
odoo/addons/account_fiscal_position_partner_type/views/res_partner.xml
odoo13_addon_account_fiscal_position_partner_type-13.0.1.1.0.dist-info/METADATA
odoo13_addon_account_fiscal_position_partner_type-13.0.1.1.0.dist-info/WHEEL
odoo13_addon_account_fiscal_position_partner_type-13.0.1.1.0.dist-info/top_level.txt
odoo13_addon_account_fiscal_position_partner_type-13.0.1.1.0.dist-info/RECORD
